etcd/__init__.py
etcd/api/__init__.py
etcd/api/authpb/auth_pb2.py
etcd/api/etcdserverpb/__init__.py
etcd/api/etcdserverpb/rpc_pb2.py
etcd/api/etcdserverpb/rpc_pb2_grpc.py
etcd/api/mvccpb/kv_pb2.py
etcd/api/versionpb/version_pb2.py
etcd_client/__init__.py
etcd_client/async_client.py
etcd_client/client.py
gogoproto/__init__.py
gogoproto/gogo_pb2.py
protoc_gen_openapiv2/__init__.py
protoc_gen_openapiv2/options/__init__.py
protoc_gen_openapiv2/options/annotations_pb2.py
protoc_gen_openapiv2/options/openapiv2_pb2.py
etcd3_async_client-0.2.0.dist-info/METADATA
etcd3_async_client-0.2.0.dist-info/WHEEL
etcd3_async_client-0.2.0.dist-info/top_level.txt
etcd3_async_client-0.2.0.dist-info/RECORD
