Metadata-Version: 2.4
Name: etcd3-async-client
Version: 0.2.0
Summary: Async Python client for etcd v3 using grpc.aio
Author-email: Anton Irshanka <irshenko@gmail.com>
License-Expression: MIT
Requires-Python: >=3.11
Requires-Dist: grpcio
Requires-Dist: grpcio-tools
Requires-Dist: protobuf
Requires-Dist: googleapis-common-protos
